zdic_parser/__init__.py
zdic_parser/parser.py
zdic_parser/parser_algorithms.py
zdic_parser/parser_exceptions/__init__.py
zdic_parser/parser_exceptions/exceptions.py
zdic_parser/type_definitions/__init__.py
zdic_parser/type_definitions/types.py
zdic_parser-0.1.1.dist-info/LICENSE
zdic_parser-0.1.1.dist-info/METADATA
zdic_parser-0.1.1.dist-info/WHEEL
zdic_parser-0.1.1.dist-info/top_level.txt
zdic_parser-0.1.1.dist-info/RECORD
