Metadata-Version: 2.2
Name: zdic_parser
Version: 0.1.1
Summary: A simple Python library to scrape and parse Chinese character data from zdic using BeautifulSoup.
Author-email: Robert L <lingrobert929@gmail.com>
License: MIT License
Project-URL: Homepage, https://github.com/TheRobertLing/zdic-parser
Project-URL: Repository, https://github.com/TheRobertLing/zdic-parser
Project-URL: Issues, https://github.com/TheRobertLing/zdic-parser/issues
License-File: LICENSE
Requires-Dist: beautifulsoup4
Requires-Dist: httpx>=0.23.0
Requires-Dist: lxml
Provides-Extra: dev
Requires-Dist: pytest; extra == "dev"
